psifospoll/__init__.py
psifospoll/psifospoll.py
psifospoll/elections/STVElection.py
psifospoll/elections/__init__.py
psifospoll/elections/election.py
psifospoll/elections/tallies/STVtally.py
psifospoll/elections/tallies/STVutils.py
psifospoll/elections/tallies/__init__.py
psifospoll/elections/tallies/tally.py
psifospoll/elections/tallies/ballots/STVballot.py
psifospoll/elections/tallies/ballots/__init__.py
psifospoll/elections/tallies/ballots/ballot.py
psifospoll-2.1.0.dist-info/METADATA
psifospoll-2.1.0.dist-info/WHEEL
psifospoll-2.1.0.dist-info/top_level.txt
psifospoll-2.1.0.dist-info/RECORD
